[
  {
    "item":1,
    "value":"Make a demo using Web Workers"
  },
  {
    "item":2,
    "value":"Make your own JSON file that you call via AJAX"
  },
  {
    "item":3,
    "value":"Make a demo using HTML5 local storage"
  },
  {
    "item":4,
    "value":"write a SASS function that uses an @if statement"
  },
  {
    "item":5,
    "value":"build a demo that converts a google spreadsheet into valid JSON"
  },
  {
    "item":6,
    "value":"Make a tutorial that teaches beginners how to use git"
  },
  {
    "item":7,
    "value":"Make a demo explaining and using web sockets"
  },
  {
    "item":8,
    "value":"Build a single page web app"
  },
  {
    "item":9,
    "value":"Design a CSS logo based off of your last name, then animate it"
  },
  {
    "item":10,
    "value":"Write an ajax function with jQuery that uses a promise as a callback"
  },
  {
    "item":11,
    "value":"Build a web app that provides definitions to standard javascript terms"
  },
  {
    "item":12,
    "value":"Build a set of SVG animated icons"
  },
  {
    "item":13,
    "value":"Make an HTML/CSS/JS metronome!"
  },
  {
    "item":14,
    "value":"Build a pacman game"
  },
  {
    "item":15,
    "value":"Build a canvas drawing app!"
  },
  {
    "item":16,
    "value":"Build a slider that uses radio buttons to make it's transitions"
  },
  {
    "item":17,
    "value":"Build a form. When a form element is filled in, make the page background change"
  },
  {
    "item":18,
    "value":"Make your own jQuery plugin!"
  },
  {
    "item":19,
    "value":"Build a calculator"
  },
  {
    "item":20,
    "value":"Build an interactive maze. Make it responsive"
  }
]